README.txt
setup.py
docs/HISTORY.txt
docs/INSTALL.txt
docs/LICENSE.GPL
docs/LICENSE.txt
wildcard/__init__.py
wildcard.level3caching.egg-info/PKG-INFO
wildcard.level3caching.egg-info/SOURCES.txt
wildcard.level3caching.egg-info/dependency_links.txt
wildcard.level3caching.egg-info/entry_points.txt
wildcard.level3caching.egg-info/namespace_packages.txt
wildcard.level3caching.egg-info/not-zip-safe
wildcard.level3caching.egg-info/requires.txt
wildcard.level3caching.egg-info/top_level.txt
wildcard/level3caching/__init__.py
wildcard/level3caching/client.py
wildcard/level3caching/configure.zcml
wildcard/level3caching/events.py
wildcard/level3caching/interfaces.py
wildcard/level3caching/level3.jpg
wildcard/level3caching/settings.py
wildcard/level3caching/tests.py
wildcard/level3caching/views.py
wildcard/level3caching/widgets.py
wildcard/level3caching/profiles/default/actions.xml
wildcard/level3caching/profiles/default/browserlayer.xml
wildcard/level3caching/profiles/default/controlpanel.xml
wildcard/level3caching/profiles/default/metadata.xml