Metadata-Version: 1.1
Name: wildcard.level3caching
Version: 1.3
Summary: provide integration for invalidations with level3
Home-page: http://svn.plone.org/svn/collective/wildcard.level3caching
Author: Nathan Van Gheem
Author-email: nathan.vangheem@wildcardcorp.com
License: GPL
Keywords: plone level3 caching cdn
Platform: UNKNOWN
Classifier: Framework :: Plone
Classifier: Programming Language :: Python
